api/__init__.py
api/official.py
css/__init__.py
css/css.py
utils/__init__.py
utils/logger.py
web/__init__.py
web/official.py
zibuyu_wechat-0.0.2.dist-info/METADATA
zibuyu_wechat-0.0.2.dist-info/WHEEL
zibuyu_wechat-0.0.2.dist-info/top_level.txt
zibuyu_wechat-0.0.2.dist-info/RECORD
