Metadata-Version: 2.1
Name: zibuyu_wechat
Version: 0.0.2
Summary: 子不语个人工具包-微信相关SDK
Home-page: https://gitee.com/zibuyu2015831/wechat-sdk
Author: 子不语
Author-email: zibuyu2015831@qq.com
License: MIT
Keywords: zibuyu,zibuyu_wechat,wechat
Classifier: License :: OSI Approved :: MIT License
Classifier: Operating System :: OS Independent
Classifier: Intended Audience :: Developers
Classifier: Programming Language :: Python :: 3.9
Classifier: Programming Language :: Python :: 3.10
Classifier: Programming Language :: Python :: 3.11
Classifier: Programming Language :: Python :: 3.12
Requires-Python: >=3.9
Requires-Dist: requests
Requires-Dist: requests-toolbelt
